PlotLinearSolverResult/__init__.py
PlotLinearSolverResult/read_continous_launching_hdf5.py
PlotLinearSolverResult/read_from_hdf5.py
plotlinearsolverresult-0.1.4.dist-info/licenses/LICENSE
plotlinearsolverresult-0.1.4.dist-info/METADATA
plotlinearsolverresult-0.1.4.dist-info/WHEEL
plotlinearsolverresult-0.1.4.dist-info/top_level.txt
plotlinearsolverresult-0.1.4.dist-info/RECORD
