Metadata-Version: 2.4
Name: PlotLinearSolverResult
Version: 0.1.4
Summary: This project is for plot LinearMSTMM solver result that is write with hdf5.
Author-email: Zhengquan Liu <liuzq_96@163.com>
License: 
Project-URL: Homepage, https://github.com/Qxxx1xx/PlotLinearSolverResult
Requires-Python: >=3.8
License-File: LICENSE
Requires-Dist: numpy
Requires-Dist: h5py
Provides-Extra: dev
Requires-Dist: click; extra == "dev"
Requires-Dist: Sphinx; extra == "dev"
Requires-Dist: coverage; extra == "dev"
Requires-Dist: awscli; extra == "dev"
Requires-Dist: flake8; extra == "dev"
Requires-Dist: python-dotenv>=0.5.1; extra == "dev"
Dynamic: license-file
